Metadata-Version: 1.1
Name: mplotly
Version: 0.1.1
Summary: Plot like pandas.DataFrame.plot with plotly
Home-page: https://github.com/xbanke/mplotly
Author: quantpy
Author-email: quantpy@qq.com
License: MIT
Keywords: plotly,mplotly
Platform: UNKNOWN
Classifier: Development Status :: 4 - Beta
Classifier: Environment :: Console
Classifier: Intended Audience :: Developers
Classifier: License :: OSI Approved :: MIT License
Classifier: Operating System :: OS Independent
Classifier: Programming Language :: Python
Classifier: Programming Language :: Python :: Implementation
Classifier: Programming Language :: Python :: 3.6
Classifier: Topic :: Software Development :: Libraries
